odoo/addons/account_journal_general_sequence/README.rst
odoo/addons/account_journal_general_sequence/__init__.py
odoo/addons/account_journal_general_sequence/__manifest__.py
odoo/addons/account_journal_general_sequence/i18n/account_journal_general_sequence.pot
odoo/addons/account_journal_general_sequence/i18n/ca_ES.po
odoo/addons/account_journal_general_sequence/i18n/es.po
odoo/addons/account_journal_general_sequence/i18n/hr.po
odoo/addons/account_journal_general_sequence/i18n/it.po
odoo/addons/account_journal_general_sequence/migrations/16.0.2.0.0/post-migration.py
odoo/addons/account_journal_general_sequence/models/__init__.py
odoo/addons/account_journal_general_sequence/models/account_journal.py
odoo/addons/account_journal_general_sequence/models/account_move.py
odoo/addons/account_journal_general_sequence/models/account_move_line.py
odoo/addons/account_journal_general_sequence/readme/CONFIGURE.md
odoo/addons/account_journal_general_sequence/readme/CONTRIBUTORS.md
odoo/addons/account_journal_general_sequence/readme/DESCRIPTION.md
odoo/addons/account_journal_general_sequence/readme/INSTALL.md
odoo/addons/account_journal_general_sequence/readme/USAGE.md
odoo/addons/account_journal_general_sequence/security/ir.model.access.csv
odoo/addons/account_journal_general_sequence/static/description/icon.png
odoo/addons/account_journal_general_sequence/static/description/index.html
odoo/addons/account_journal_general_sequence/tests/__init__.py
odoo/addons/account_journal_general_sequence/tests/test_numbering.py
odoo/addons/account_journal_general_sequence/views/account_journal.xml
odoo/addons/account_journal_general_sequence/views/account_move.xml
odoo/addons/account_journal_general_sequence/views/account_move_line.xml
odoo/addons/account_journal_general_sequence/wizards/__init__.py
odoo/addons/account_journal_general_sequence/wizards/account_move_renumber_wizard.py
odoo/addons/account_journal_general_sequence/wizards/account_move_renumber_wizard_views.xml
odoo_addon_account_journal_general_sequence-18.0.1.0.1.dist-info/METADATA
odoo_addon_account_journal_general_sequence-18.0.1.0.1.dist-info/WHEEL
odoo_addon_account_journal_general_sequence-18.0.1.0.1.dist-info/top_level.txt
odoo_addon_account_journal_general_sequence-18.0.1.0.1.dist-info/RECORD
