Metadata-Version: 2.1
Name: odoo-addon-account_journal_general_sequence
Version: 18.0.1.0.1
Requires-Python: >=3.10
Requires-Dist: freezegun
Requires-Dist: odoo==18.0.*
Summary: Add configurable sequence to account moves, per journal
Home-page: https://github.com/OCA/account-financial-tools
License: LGPL-3
Author: Moduon, Odoo Community Association (OCA)
Author-email: support@odoo-community.org
Classifier: Programming Language :: Python
Classifier: Framework :: Odoo
Classifier: Framework :: Odoo :: 18.0
Classifier: License :: OSI Approved :: GNU Lesser General Public License v3 (LGPLv3)
